{
  "count": 8,
  "totalState": 37,
  "outages": [
    {
      "icon": "standard",
      "longitude": -111.935,
      "latitude": 40.396,
      "etr": "Before 07:30 PM on 06/01",
      "outCount": 2,
      "custOut": 7,
      "cause": "Damaged Equipment",
      "crewStatus": "Crews Notified",
      "reported": "12:48 PM on 06/01",
      "zip": "84045"
    },
    {
      "icon": "standard",
      "longitude": -112.354,
      "latitude": 40.523,
      "etr": "Before 08:00 PM on 06/01",
      "outCount": 1,
      "custOut": 1,
      "cause": "Investigating",
      "crewStatus": "Crews Notified",
      "reported": "01:49 PM on 06/01",
      "zip": "84074"
    },
    {
      "icon": "standard",
      "longitude": -112.298,
      "latitude": 40.538,
      "etr": "Before 08:00 PM on 06/01",
      "outCount": 1,
      "custOut": 1,
      "cause": "Investigating",
      "crewStatus": "Crews Notified",
      "reported": "01:48 PM on 06/01",
      "zip": "84074"
    },
    {
      "icon": "standard",
      "longitude": -111.9,
      "latitude": 40.614,
      "etr": "Before 07:00 PM on 06/01",
      "outCount": 1,
      "custOut": 1,
      "cause": "Investigating",
      "crewStatus": "Crews Arrived",
      "reported": "03:38 PM on 06/01",
      "zip": "84047"
    },
    {
      "icon": "standard",
      "longitude": -111.805,
      "latitude": 40.658,
      "etr": "Before 06:30 PM on 06/01",
      "outCount": 1,
      "custOut": 25,
      "cause": "Damaged Equipment",
      "crewStatus": "Crews Notified",
      "reported": "03:28 PM on 06/01",
      "zip": "84117"
    },
    {
      "icon": "standard",
      "longitude": -111.844,
      "latitude": 40.702,
      "etr": "Before 07:00 PM on 06/01",
      "outCount": 1,
      "custOut": 1,
      "cause": "Investigating",
      "crewStatus": "Crews Notified",
      "reported": "03:55 PM on 06/01",
      "zip": "84109"
    },
    {
      "icon": "standard",
      "longitude": -112.022,
      "latitude": 41.178,
      "etr": "Before 07:00 PM on 06/01",
      "outCount": 1,
      "custOut": 1,
      "cause": "Investigating",
      "crewStatus": "Crews Notified",
      "reported": "12:51 PM on 06/01",
      "zip": "84067"
    }
  ],
  "zips": [
    {
      "zipCode": "84045",
      "outCountPlan": 0,
      "outCountUnplan": 2,
      "custOutPlan": 0,
      "custOutUnplan": 7
    },
    {
      "zipCode": "84047",
      "outCountPlan": 0,
      "outCountUnplan": 1,
      "custOutPlan": 0,
      "custOutUnplan": 1
    },
    {
      "zipCode": "84067",
      "outCountPlan": 0,
      "outCountUnplan": 1,
      "custOutPlan": 0,
      "custOutUnplan": 1
    },
    {
      "zipCode": "84074",
      "outCountPlan": 0,
      "outCountUnplan": 2,
      "custOutPlan": 0,
      "custOutUnplan": 2
    },
    {
      "zipCode": "84109",
      "outCountPlan": 0,
      "outCountUnplan": 1,
      "custOutPlan": 0,
      "custOutUnplan": 1
    },
    {
      "zipCode": "84117",
      "outCountPlan": 0,
      "outCountUnplan": 1,
      "custOutPlan": 0,
      "custOutUnplan": 25
    }
  ],
  "counties": [
    {
      "countyName": "Salt Lake",
      "outCountPlan": 0,
      "outCountUnplan": 3,
      "custOutPlan": 0,
      "custOutUnplan": 27
    },
    {
      "countyName": "Tooele",
      "outCountPlan": 0,
      "outCountUnplan": 2,
      "custOutPlan": 0,
      "custOutUnplan": 2
    },
    {
      "countyName": "Utah",
      "outCountPlan": 0,
      "outCountUnplan": 2,
      "custOutPlan": 0,
      "custOutUnplan": 7
    },
    {
      "countyName": "Weber",
      "outCountPlan": 0,
      "outCountUnplan": 1,
      "custOutPlan": 0,
      "custOutUnplan": 1
    }
  ]
}
