{
  "count": 18,
  "totalState": 279,
  "outages": [
    {
      "icon": "planned",
      "longitude": -111.687,
      "latitude": 40.268,
      "etr": "Before 01:00 PM on 08/07",
      "outCount": 1,
      "custOut": 32,
      "cause": "Planned Maintenance",
      "crewStatus": "Crews Arrived",
      "reported": "07:23 AM on 08/07",
      "zip": "84097, 84604"
    },
    {
      "icon": "standard",
      "longitude": -111.842,
      "latitude": 40.571,
      "etr": "Assessing",
      "outCount": 1,
      "custOut": 1,
      "cause": "Investigating",
      "crewStatus": "Crews Notified",
      "reported": "07:44 AM on 08/07",
      "zip": "84092"
    },
    {
      "icon": "standard",
      "longitude": -111.5,
      "latitude": 40.617,
      "etr": "Before 11:30 AM on 08/07",
      "outCount": 1,
      "custOut": 1,
      "cause": "Investigating",
      "crewStatus": "Crews Notified",
      "reported": "07:17 AM on 08/07",
      "zip": "84060"
    },
    {
      "icon": "standard",
      "longitude": -111.843,
      "latitude": 40.644,
      "etr": "Before 10:00 AM on 08/07",
      "outCount": 1,
      "custOut": 1,
      "cause": "Investigating",
      "crewStatus": "Crews Notified",
      "reported": "06:36 AM on 08/07",
      "zip": "84121"
    },
    {
      "icon": "standard",
      "longitude": -112.014,
      "latitude": 40.657,
      "etr": "Before 09:30 AM on 08/07",
      "outCount": 2,
      "custOut": 2,
      "cause": "Investigating",
      "crewStatus": "Crews Notified",
      "reported": "06:04 AM on 08/07",
      "zip": "84118"
    },
    {
      "icon": "standard",
      "longitude": -111.825,
      "latitude": 40.716,
      "etr": "Before 11:00 AM on 08/07",
      "outCount": 1,
      "custOut": 1,
      "cause": "Investigating",
      "crewStatus": "Crews Notified",
      "reported": "07:37 AM on 08/07",
      "zip": "84109"
    },
    {
      "icon": "standard",
      "longitude": -111.922,
      "latitude": 40.86,
      "etr": "Before 11:00 AM on 08/07",
      "outCount": 1,
      "custOut": 1,
      "cause": "Investigating",
      "crewStatus": "Crews Notified",
      "reported": "06:41 AM on 08/07",
      "zip": "84054"
    },
    {
      "icon": "standard",
      "longitude": -111.963,
      "latitude": 41.078,
      "etr": "Before 12:00 PM on 08/07",
      "outCount": 2,
      "custOut": 195,
      "cause": "Multiple outages in the area",
      "crewStatus": "Crews Arrived",
      "reported": "05:46 AM on 08/07",
      "zip": "84041"
    },
    {
      "icon": "standard",
      "longitude": -111.926,
      "latitude": 41.121,
      "etr": "Before 02:00 PM on 08/07",
      "outCount": 1,
      "custOut": 1,
      "cause": "Investigating",
      "crewStatus": "Crews Notified",
      "reported": "07:33 AM on 08/07",
      "zip": "84405"
    },
    {
      "icon": "standard",
      "longitude": -112.061,
      "latitude": 41.164,
      "etr": "Before 10:00 AM on 08/07",
      "outCount": 1,
      "custOut": 19,
      "cause": "Damaged Equipment",
      "crewStatus": "Crews Notified",
      "reported": "12:16 AM on 08/07",
      "zip": "84067"
    },
    {
      "icon": "standard",
      "longitude": -111.965,
      "latitude": 41.164,
      "etr": "Before 12:30 PM on 08/07",
      "outCount": 1,
      "custOut": 1,
      "cause": "Investigating",
      "crewStatus": "Crews Notified",
      "reported": "06:10 AM on 08/07",
      "zip": "84405"
    },
    {
      "icon": "standard",
      "longitude": -112.003,
      "latitude": 41.179,
      "etr": "Before 10:30 AM on 08/07",
      "outCount": 1,
      "custOut": 1,
      "cause": "Investigating",
      "crewStatus": "Crews Notified",
      "reported": "10:26 PM on 08/06",
      "zip": "84405"
    },
    {
      "icon": "standard",
      "longitude": -111.985,
      "latitude": 41.266,
      "etr": "Before 11:30 AM on 08/07",
      "outCount": 1,
      "custOut": 20,
      "cause": "Damaged Equipment",
      "crewStatus": "Crews Notified",
      "reported": "08:58 PM on 08/06",
      "zip": "84404"
    },
    {
      "icon": "standard",
      "longitude": -111.809,
      "latitude": 41.278,
      "etr": "Before 02:00 AM on 08/08",
      "outCount": 1,
      "custOut": 1,
      "cause": "Trees",
      "crewStatus": "Crews Notified",
      "reported": "08:54 PM on 08/06",
      "zip": "84310"
    },
    {
      "icon": "standard",
      "longitude": -111.947,
      "latitude": 41.281,
      "etr": "Assessing",
      "outCount": 2,
      "custOut": 2,
      "cause": "Multiple outages in the area",
      "crewStatus": "Crews Notified",
      "reported": "07:07 PM on 08/06",
      "zip": "84404"
    }
  ],
  "zips": [
    {
      "zipCode": "84041",
      "outCountPlan": 0,
      "outCountUnplan": 2,
      "custOutPlan": 0,
      "custOutUnplan": 195
    },
    {
      "zipCode": "84054",
      "outCountPlan": 0,
      "outCountUnplan": 1,
      "custOutPlan": 0,
      "custOutUnplan": 1
    },
    {
      "zipCode": "84060",
      "outCountPlan": 0,
      "outCountUnplan": 1,
      "custOutPlan": 0,
      "custOutUnplan": 1
    },
    {
      "zipCode": "84067",
      "outCountPlan": 0,
      "outCountUnplan": 1,
      "custOutPlan": 0,
      "custOutUnplan": 19
    },
    {
      "zipCode": "84092",
      "outCountPlan": 0,
      "outCountUnplan": 1,
      "custOutPlan": 0,
      "custOutUnplan": 1
    },
    {
      "zipCode": "84097",
      "outCountPlan": 1,
      "outCountUnplan": 0,
      "custOutPlan": 32,
      "custOutUnplan": 0
    },
    {
      "zipCode": "84109",
      "outCountPlan": 0,
      "outCountUnplan": 1,
      "custOutPlan": 0,
      "custOutUnplan": 1
    },
    {
      "zipCode": "84118",
      "outCountPlan": 0,
      "outCountUnplan": 2,
      "custOutPlan": 0,
      "custOutUnplan": 2
    },
    {
      "zipCode": "84121",
      "outCountPlan": 0,
      "outCountUnplan": 1,
      "custOutPlan": 0,
      "custOutUnplan": 1
    },
    {
      "zipCode": "84310",
      "outCountPlan": 0,
      "outCountUnplan": 1,
      "custOutPlan": 0,
      "custOutUnplan": 1
    },
    {
      "zipCode": "84404",
      "outCountPlan": 0,
      "outCountUnplan": 3,
      "custOutPlan": 0,
      "custOutUnplan": 22
    },
    {
      "zipCode": "84405",
      "outCountPlan": 0,
      "outCountUnplan": 3,
      "custOutPlan": 0,
      "custOutUnplan": 3
    }
  ],
  "counties": [
    {
      "countyName": "Davis",
      "outCountPlan": 0,
      "outCountUnplan": 4,
      "custOutPlan": 0,
      "custOutUnplan": 197
    },
    {
      "countyName": "Salt Lake",
      "outCountPlan": 0,
      "outCountUnplan": 5,
      "custOutPlan": 0,
      "custOutUnplan": 5
    },
    {
      "countyName": "Summit",
      "outCountPlan": 0,
      "outCountUnplan": 1,
      "custOutPlan": 0,
      "custOutUnplan": 1
    },
    {
      "countyName": "Utah",
      "outCountPlan": 1,
      "outCountUnplan": 0,
      "custOutPlan": 32,
      "custOutUnplan": 0
    },
    {
      "countyName": "Weber",
      "outCountPlan": 0,
      "outCountUnplan": 7,
      "custOutPlan": 0,
      "custOutUnplan": 44
    }
  ]
}
