{
  "count": 3,
  "totalState": 80,
  "outages": [
    {
      "icon": "standard",
      "longitude": -111.995,
      "latitude": 40.657,
      "etr": "Before 08:30 AM on 09/18",
      "outCount": 1,
      "custOut": 67,
      "cause": "Investigating",
      "crewStatus": "Crews Notified",
      "reported": "05:16 AM on 09/18",
      "zip": "84118"
    },
    {
      "icon": "standard",
      "longitude": -111.996,
      "latitude": 40.671,
      "etr": "Before 10:00 AM on 09/18",
      "outCount": 1,
      "custOut": 12,
      "cause": "Investigating",
      "crewStatus": "Crews Notified",
      "reported": "05:31 AM on 09/18",
      "zip": "84118"
    },
    {
      "icon": "standard",
      "longitude": -112.015,
      "latitude": 40.7,
      "etr": "Before 09:00 AM on 09/18",
      "outCount": 1,
      "custOut": 1,
      "cause": "Investigating",
      "crewStatus": "Crews Notified",
      "reported": "05:48 AM on 09/18",
      "zip": "84120"
    }
  ],
  "zips": [
    {
      "zipCode": "84118",
      "outCountPlan": 0,
      "outCountUnplan": 2,
      "custOutPlan": 0,
      "custOutUnplan": 79
    },
    {
      "zipCode": "84120",
      "outCountPlan": 0,
      "outCountUnplan": 1,
      "custOutPlan": 0,
      "custOutUnplan": 1
    }
  ],
  "counties": [
    {
      "countyName": "Salt Lake",
      "outCountPlan": 0,
      "outCountUnplan": 3,
      "custOutPlan": 0,
      "custOutUnplan": 80
    }
  ]
}
