{
  "count": 1,
  "totalState": 3,
  "outages": [
    {
      "icon": "standard",
      "longitude": -109.648,
      "latitude": 41.632,
      "etr": "Before 09:30 PM on 01/31",
      "outCount": 1,
      "custOut": 3,
      "cause": "Investigating",
      "crewStatus": "Crews Notified",
      "reported": "06:19 PM on 01/31",
      "zip": "82935"
    }
  ],
  "zips": [
    {
      "zipCode": "82935",
      "outCountPlan": 0,
      "outCountUnplan": 1,
      "custOutPlan": 0,
      "custOutUnplan": 3
    }
  ],
  "counties": [
    {
      "countyName": "Sweetwater",
      "outCountPlan": 0,
      "outCountUnplan": 1,
      "custOutPlan": 0,
      "custOutUnplan": 3
    }
  ]
}
