{
  "count": 19,
  "totalState": 854,
  "outages": [
    {
      "icon": "standard",
      "longitude": -113.05,
      "latitude": 37.714,
      "etr": "Before 11:00 PM on 08/12",
      "outCount": 1,
      "custOut": 1,
      "cause": "Investigating",
      "crewStatus": "Crews Notified",
      "reported": "08:02 PM on 08/12",
      "zip": "84721"
    },
    {
      "icon": "standard",
      "longitude": -110.855,
      "latitude": 39.632,
      "etr": "Assessing",
      "outCount": 1,
      "custOut": 3,
      "cause": "Investigating",
      "crewStatus": "Crews Arrived",
      "reported": "03:59 PM on 08/12",
      "zip": "84526"
    },
    {
      "icon": "standard",
      "longitude": -111.687,
      "latitude": 40.297,
      "etr": "Assessing",
      "outCount": 1,
      "custOut": 5,
      "cause": "Investigating",
      "crewStatus": "Crews Arrived",
      "reported": "04:31 PM on 08/12",
      "zip": "84058"
    },
    {
      "icon": "standard",
      "longitude": -111.975,
      "latitude": 40.556,
      "etr": "Before 11:30 PM on 08/12",
      "outCount": 1,
      "custOut": 12,
      "cause": "Damaged Equipment",
      "crewStatus": "Crews Notified",
      "reported": "07:04 PM on 08/12",
      "zip": "84009"
    },
    {
      "icon": "standard",
      "longitude": -111.88,
      "latitude": 40.571,
      "etr": "Before 08:30 PM on 08/12",
      "outCount": 1,
      "custOut": 1,
      "cause": "Damaged Equipment",
      "crewStatus": "Crews Arrived",
      "reported": "06:30 PM on 08/12",
      "zip": "84070"
    },
    {
      "icon": "standard",
      "longitude": -111.918,
      "latitude": 40.585,
      "etr": "Before 11:00 PM on 08/12",
      "outCount": 1,
      "custOut": 1,
      "cause": "Investigating",
      "crewStatus": "Crews Notified",
      "reported": "07:46 PM on 08/12",
      "zip": "84088"
    },
    {
      "icon": "standard",
      "longitude": -112.318,
      "latitude": 40.61,
      "etr": "Before 06:30 AM on 08/13",
      "outCount": 1,
      "custOut": 1,
      "cause": "Investigating",
      "crewStatus": "Crews Notified",
      "reported": "07:28 PM on 08/12",
      "zip": "84074"
    },
    {
      "icon": "standard",
      "longitude": -111.939,
      "latitude": 40.686,
      "etr": "Before 12:00 AM on 08/13",
      "outCount": 1,
      "custOut": 24,
      "cause": "Investigating",
      "crewStatus": "Crews Notified",
      "reported": "07:33 PM on 08/12",
      "zip": "84119"
    },
    {
      "icon": "standard",
      "longitude": -111.996,
      "latitude": 40.7,
      "etr": "Before 11:30 PM on 08/12",
      "outCount": 1,
      "custOut": 1,
      "cause": "Investigating",
      "crewStatus": "Crews Notified",
      "reported": "08:27 PM on 08/12",
      "zip": "84120"
    },
    {
      "icon": "standard",
      "longitude": -111.863,
      "latitude": 40.701,
      "etr": "Before 10:30 PM on 08/12",
      "outCount": 1,
      "custOut": 1,
      "cause": "Investigating",
      "crewStatus": "Crews Notified",
      "reported": "04:24 PM on 08/12",
      "zip": "84106"
    },
    {
      "icon": "standard",
      "longitude": -111.844,
      "latitude": 40.716,
      "etr": "Before 10:00 PM on 08/12",
      "outCount": 1,
      "custOut": 1,
      "cause": "Investigating",
      "crewStatus": "Crews Notified",
      "reported": "09:40 AM on 08/12",
      "zip": "84106"
    },
    {
      "icon": "standard",
      "longitude": -111.806,
      "latitude": 40.745,
      "etr": "Assessing",
      "outCount": 1,
      "custOut": 3,
      "cause": "Damaged Equipment",
      "crewStatus": "Crews Notified",
      "reported": "03:00 PM on 08/12",
      "zip": "84108"
    },
    {
      "icon": "standard",
      "longitude": -111.94,
      "latitude": 40.759,
      "etr": "Before 11:00 PM on 08/12",
      "outCount": 1,
      "custOut": 2,
      "cause": "Emergency Repair",
      "crewStatus": "Crews Arrived",
      "reported": "08:06 PM on 08/12",
      "zip": "84104"
    },
    {
      "icon": "standard",
      "longitude": -111.883,
      "latitude": 40.774,
      "etr": "Before 08:30 PM on 08/12",
      "outCount": 1,
      "custOut": 1,
      "cause": "Investigating",
      "crewStatus": "Crews Notified",
      "reported": "05:03 PM on 08/12",
      "zip": "84103"
    },
    {
      "icon": "standard",
      "longitude": -111.903,
      "latitude": 40.846,
      "etr": "Before 09:00 PM on 08/12",
      "outCount": 1,
      "custOut": 3,
      "cause": "Investigating",
      "crewStatus": "Crews Notified",
      "reported": "04:53 PM on 08/12",
      "zip": "84054"
    },
    {
      "icon": "standard",
      "longitude": -111.359,
      "latitude": 40.943,
      "etr": "Assessing",
      "outCount": 1,
      "custOut": 1,
      "cause": "Damaged Equipment",
      "crewStatus": "Crews Notified",
      "reported": "05:37 PM on 08/12",
      "zip": "84017"
    },
    {
      "icon": "standard",
      "longitude": -112.061,
      "latitude": 41.178,
      "etr": "Assessing",
      "outCount": 2,
      "custOut": 148,
      "cause": "Multiple outages in the area",
      "crewStatus": "Crews Notified",
      "reported": "12:12 PM on 08/12",
      "zip": "84067"
    },
    {
      "icon": "ess",
      "longitude": -112.147,
      "latitude": 41.743,
      "etr": "Before 11:00 PM on 08/12",
      "outCount": 1,
      "custOut": 645,
      "cause": "Enhanced Safety Settings",
      "crewStatus": "Monitoring Conditions",
      "reported": "07:42 PM on 08/12",
      "zip": "84334, 84312, 84311, 84306"
    }
  ],
  "zips": [
    {
      "zipCode": "84009",
      "outCountPlan": 0,
      "outCountUnplan": 1,
      "custOutPlan": 0,
      "custOutUnplan": 12
    },
    {
      "zipCode": "84017",
      "outCountPlan": 0,
      "outCountUnplan": 1,
      "custOutPlan": 0,
      "custOutUnplan": 1
    },
    {
      "zipCode": "84054",
      "outCountPlan": 0,
      "outCountUnplan": 1,
      "custOutPlan": 0,
      "custOutUnplan": 3
    },
    {
      "zipCode": "84058",
      "outCountPlan": 0,
      "outCountUnplan": 1,
      "custOutPlan": 0,
      "custOutUnplan": 5
    },
    {
      "zipCode": "84067",
      "outCountPlan": 0,
      "outCountUnplan": 2,
      "custOutPlan": 0,
      "custOutUnplan": 148
    },
    {
      "zipCode": "84070",
      "outCountPlan": 0,
      "outCountUnplan": 1,
      "custOutPlan": 0,
      "custOutUnplan": 1
    },
    {
      "zipCode": "84074",
      "outCountPlan": 0,
      "outCountUnplan": 1,
      "custOutPlan": 0,
      "custOutUnplan": 1
    },
    {
      "zipCode": "84088",
      "outCountPlan": 0,
      "outCountUnplan": 1,
      "custOutPlan": 0,
      "custOutUnplan": 1
    },
    {
      "zipCode": "84103",
      "outCountPlan": 0,
      "outCountUnplan": 1,
      "custOutPlan": 0,
      "custOutUnplan": 1
    },
    {
      "zipCode": "84104",
      "outCountPlan": 0,
      "outCountUnplan": 1,
      "custOutPlan": 0,
      "custOutUnplan": 2
    },
    {
      "zipCode": "84106",
      "outCountPlan": 0,
      "outCountUnplan": 2,
      "custOutPlan": 0,
      "custOutUnplan": 2
    },
    {
      "zipCode": "84108",
      "outCountPlan": 0,
      "outCountUnplan": 1,
      "custOutPlan": 0,
      "custOutUnplan": 3
    },
    {
      "zipCode": "84119",
      "outCountPlan": 0,
      "outCountUnplan": 1,
      "custOutPlan": 0,
      "custOutUnplan": 24
    },
    {
      "zipCode": "84120",
      "outCountPlan": 0,
      "outCountUnplan": 1,
      "custOutPlan": 0,
      "custOutUnplan": 1
    },
    {
      "zipCode": "84306",
      "outCountPlan": 0,
      "outCountUnplan": 1,
      "custOutPlan": 0,
      "custOutUnplan": 25
    },
    {
      "zipCode": "84311",
      "outCountPlan": 0,
      "outCountUnplan": 1,
      "custOutPlan": 0,
      "custOutUnplan": 12
    },
    {
      "zipCode": "84312",
      "outCountPlan": 0,
      "outCountUnplan": 1,
      "custOutPlan": 0,
      "custOutUnplan": 526
    },
    {
      "zipCode": "84334",
      "outCountPlan": 0,
      "outCountUnplan": 1,
      "custOutPlan": 0,
      "custOutUnplan": 82
    },
    {
      "zipCode": "84526",
      "outCountPlan": 0,
      "outCountUnplan": 1,
      "custOutPlan": 0,
      "custOutUnplan": 3
    },
    {
      "zipCode": "84721",
      "outCountPlan": 0,
      "outCountUnplan": 1,
      "custOutPlan": 0,
      "custOutUnplan": 1
    }
  ],
  "counties": [
    {
      "countyName": "Box Elder",
      "outCountPlan": 0,
      "outCountUnplan": 1,
      "custOutPlan": 0,
      "custOutUnplan": 645
    },
    {
      "countyName": "Carbon",
      "outCountPlan": 0,
      "outCountUnplan": 1,
      "custOutPlan": 0,
      "custOutUnplan": 3
    },
    {
      "countyName": "Davis",
      "outCountPlan": 0,
      "outCountUnplan": 1,
      "custOutPlan": 0,
      "custOutUnplan": 3
    },
    {
      "countyName": "Iron",
      "outCountPlan": 0,
      "outCountUnplan": 1,
      "custOutPlan": 0,
      "custOutUnplan": 1
    },
    {
      "countyName": "Salt Lake",
      "outCountPlan": 0,
      "outCountUnplan": 10,
      "custOutPlan": 0,
      "custOutUnplan": 47
    },
    {
      "countyName": "Summit",
      "outCountPlan": 0,
      "outCountUnplan": 1,
      "custOutPlan": 0,
      "custOutUnplan": 1
    },
    {
      "countyName": "Tooele",
      "outCountPlan": 0,
      "outCountUnplan": 1,
      "custOutPlan": 0,
      "custOutUnplan": 1
    },
    {
      "countyName": "Utah",
      "outCountPlan": 0,
      "outCountUnplan": 1,
      "custOutPlan": 0,
      "custOutUnplan": 5
    },
    {
      "countyName": "Weber",
      "outCountPlan": 0,
      "outCountUnplan": 2,
      "custOutPlan": 0,
      "custOutUnplan": 148
    }
  ]
}
