{
  "count": 4,
  "totalState": 11,
  "outages": [
    {
      "icon": "standard",
      "longitude": -111.668,
      "latitude": 40.297,
      "etr": "Before 07:00 PM on 04/04",
      "outCount": 1,
      "custOut": 1,
      "cause": "Investigating",
      "crewStatus": "Crews Notified",
      "reported": "04:08 PM on 04/04",
      "zip": "84097"
    },
    {
      "icon": "planned",
      "longitude": -111.403,
      "latitude": 40.37,
      "etr": "Before 05:30 PM on 04/04",
      "outCount": 1,
      "custOut": 8,
      "cause": "Planned Maintenance",
      "crewStatus": "Crews Arrived",
      "reported": "11:38 AM on 04/04",
      "zip": "84082"
    },
    {
      "icon": "standard",
      "longitude": -112.053,
      "latitude": 40.7,
      "etr": "Before 05:30 PM on 04/04",
      "outCount": 1,
      "custOut": 1,
      "cause": "Investigating",
      "crewStatus": "Crews Arrived",
      "reported": "02:21 PM on 04/04",
      "zip": "84128"
    },
    {
      "icon": "standard",
      "longitude": -111.844,
      "latitude": 40.745,
      "etr": "Before 05:30 PM on 04/04",
      "outCount": 1,
      "custOut": 1,
      "cause": "Investigating",
      "crewStatus": "Crews Notified",
      "reported": "02:03 PM on 04/04",
      "zip": "84108"
    }
  ],
  "zips": [
    {
      "zipCode": "84082",
      "outCountPlan": 1,
      "outCountUnplan": 0,
      "custOutPlan": 8,
      "custOutUnplan": 0
    },
    {
      "zipCode": "84097",
      "outCountPlan": 0,
      "outCountUnplan": 1,
      "custOutPlan": 0,
      "custOutUnplan": 1
    },
    {
      "zipCode": "84108",
      "outCountPlan": 0,
      "outCountUnplan": 1,
      "custOutPlan": 0,
      "custOutUnplan": 1
    },
    {
      "zipCode": "84128",
      "outCountPlan": 0,
      "outCountUnplan": 1,
      "custOutPlan": 0,
      "custOutUnplan": 1
    }
  ],
  "counties": [
    {
      "countyName": "Salt Lake",
      "outCountPlan": 0,
      "outCountUnplan": 2,
      "custOutPlan": 0,
      "custOutUnplan": 2
    },
    {
      "countyName": "Utah",
      "outCountPlan": 0,
      "outCountUnplan": 1,
      "custOutPlan": 0,
      "custOutUnplan": 1
    },
    {
      "countyName": "Wasatch",
      "outCountPlan": 1,
      "outCountUnplan": 0,
      "custOutPlan": 8,
      "custOutUnplan": 0
    }
  ]
}
