{
  "count": 4,
  "totalState": 738,
  "outages": [
    {
      "icon": "standard",
      "longitude": -109.247,
      "latitude": 41.634,
      "etr": "Before 10:00 PM on 07/15",
      "outCount": 1,
      "custOut": 567,
      "cause": "Wind",
      "crewStatus": "Crews Notified",
      "reported": "06:55 PM on 07/15",
      "zip": "82901"
    },
    {
      "icon": "standard",
      "longitude": -109.286,
      "latitude": 41.634,
      "etr": "Before 10:00 PM on 07/15",
      "outCount": 1,
      "custOut": 1,
      "cause": "Investigating",
      "crewStatus": "Crews Notified",
      "reported": "06:34 PM on 07/15",
      "zip": "82901"
    },
    {
      "icon": "standard",
      "longitude": -109.266,
      "latitude": 41.648,
      "etr": "Before 10:00 PM on 07/15",
      "outCount": 1,
      "custOut": 1,
      "cause": "Investigating",
      "crewStatus": "Crews Notified",
      "reported": "06:40 PM on 07/15",
      "zip": "82901"
    },
    {
      "icon": "standard",
      "longitude": -108.232,
      "latitude": 43.642,
      "etr": "Before 10:00 PM on 07/15",
      "outCount": 1,
      "custOut": 169,
      "cause": "Investigating",
      "crewStatus": "Crews Notified",
      "reported": "06:33 PM on 07/15",
      "zip": "82649, 82443"
    }
  ],
  "zips": [
    {
      "zipCode": "82443",
      "outCountPlan": 0,
      "outCountUnplan": 1,
      "custOutPlan": 0,
      "custOutUnplan": 168
    },
    {
      "zipCode": "82649",
      "outCountPlan": 0,
      "outCountUnplan": 1,
      "custOutPlan": 0,
      "custOutUnplan": 1
    },
    {
      "zipCode": "82901",
      "outCountPlan": 0,
      "outCountUnplan": 3,
      "custOutPlan": 0,
      "custOutUnplan": 569
    }
  ],
  "counties": [
    {
      "countyName": "Hot Springs",
      "outCountPlan": 0,
      "outCountUnplan": 1,
      "custOutPlan": 0,
      "custOutUnplan": 167
    },
    {
      "countyName": "Sweetwater",
      "outCountPlan": 0,
      "outCountUnplan": 3,
      "custOutPlan": 0,
      "custOutUnplan": 569
    },
    {
      "countyName": "Washakie",
      "outCountPlan": 0,
      "outCountUnplan": 1,
      "custOutPlan": 0,
      "custOutUnplan": 2
    }
  ]
}
