{
  "count": 4,
  "totalState": 549,
  "outages": [
    {
      "icon": "standard",
      "longitude": -109.229,
      "latitude": 41.604,
      "etr": "Assessing",
      "outCount": 1,
      "custOut": 1,
      "cause": "Investigating",
      "crewStatus": "Crews Notified",
      "reported": "09:24 AM on 07/01",
      "zip": "82901"
    },
    {
      "icon": "ess",
      "longitude": -110.214,
      "latitude": 42.333,
      "etr": "Before 06:30 PM on 07/01",
      "outCount": 1,
      "custOut": 80,
      "cause": "Enhanced Safety Settings",
      "crewStatus": "Monitoring Conditions",
      "reported": "01:46 PM on 07/01",
      "zip": "83123, 83113"
    },
    {
      "icon": "standard",
      "longitude": -105.907,
      "latitude": 42.869,
      "etr": "Before 11:00 PM on 07/01",
      "outCount": 1,
      "custOut": 1,
      "cause": "Investigating",
      "crewStatus": "Crews Notified",
      "reported": "12:16 PM on 07/01",
      "zip": "82637"
    },
    {
      "icon": "standard",
      "longitude": -106.177,
      "latitude": 42.893,
      "etr": "Before 05:30 PM on 07/01",
      "outCount": 1,
      "custOut": 467,
      "cause": "Investigating",
      "crewStatus": "Crews Notified",
      "reported": "02:09 PM on 07/01",
      "zip": "82601, 82636"
    }
  ],
  "zips": [
    {
      "zipCode": "82601",
      "outCountPlan": 0,
      "outCountUnplan": 1,
      "custOutPlan": 0,
      "custOutUnplan": 2
    },
    {
      "zipCode": "82636",
      "outCountPlan": 0,
      "outCountUnplan": 1,
      "custOutPlan": 0,
      "custOutUnplan": 465
    },
    {
      "zipCode": "82637",
      "outCountPlan": 0,
      "outCountUnplan": 1,
      "custOutPlan": 0,
      "custOutUnplan": 1
    },
    {
      "zipCode": "82901",
      "outCountPlan": 0,
      "outCountUnplan": 1,
      "custOutPlan": 0,
      "custOutUnplan": 1
    },
    {
      "zipCode": "83113",
      "outCountPlan": 0,
      "outCountUnplan": 1,
      "custOutPlan": 0,
      "custOutUnplan": 56
    },
    {
      "zipCode": "83123",
      "outCountPlan": 0,
      "outCountUnplan": 1,
      "custOutPlan": 0,
      "custOutUnplan": 24
    }
  ],
  "counties": [
    {
      "countyName": "Converse",
      "outCountPlan": 0,
      "outCountUnplan": 1,
      "custOutPlan": 0,
      "custOutUnplan": 1
    },
    {
      "countyName": "Natrona",
      "outCountPlan": 0,
      "outCountUnplan": 1,
      "custOutPlan": 0,
      "custOutUnplan": 467
    },
    {
      "countyName": "Sublette",
      "outCountPlan": 0,
      "outCountUnplan": 1,
      "custOutPlan": 0,
      "custOutUnplan": 80
    },
    {
      "countyName": "Sweetwater",
      "outCountPlan": 0,
      "outCountUnplan": 1,
      "custOutPlan": 0,
      "custOutUnplan": 1
    }
  ]
}
