{
  "count": 6,
  "totalState": 6,
  "outages": [
    {
      "icon": "standard",
      "longitude": -105.57,
      "latitude": 41.258,
      "etr": "Before 11:00 AM on 02/21",
      "outCount": 2,
      "custOut": 2,
      "cause": "Investigating",
      "crewStatus": "Crews Notified",
      "reported": "05:09 AM on 02/21",
      "zip": "82070"
    },
    {
      "icon": "standard",
      "longitude": -105.589,
      "latitude": 41.259,
      "etr": "Before 11:00 AM on 02/21",
      "outCount": 2,
      "custOut": 2,
      "cause": "Investigating",
      "crewStatus": "Crews Notified",
      "reported": "05:14 AM on 02/21",
      "zip": "82070"
    },
    {
      "icon": "standard",
      "longitude": -105.588,
      "latitude": 41.273,
      "etr": "Before 11:00 AM on 02/21",
      "outCount": 1,
      "custOut": 1,
      "cause": "Investigating",
      "crewStatus": "Crews Notified",
      "reported": "05:27 AM on 02/21",
      "zip": "82070"
    },
    {
      "icon": "standard",
      "longitude": -105.607,
      "latitude": 41.274,
      "etr": "Before 11:00 AM on 02/21",
      "outCount": 1,
      "custOut": 1,
      "cause": "Investigating",
      "crewStatus": "Crews Notified",
      "reported": "05:13 AM on 02/21",
      "zip": "82070"
    }
  ],
  "zips": [
    {
      "zipCode": "82070",
      "outCountPlan": 0,
      "outCountUnplan": 6,
      "custOutPlan": 0,
      "custOutUnplan": 6
    }
  ],
  "counties": [
    {
      "countyName": "Albany",
      "outCountPlan": 0,
      "outCountUnplan": 6,
      "custOutPlan": 0,
      "custOutUnplan": 6
    }
  ]
}
