{
  "count": 6,
  "totalState": 2875,
  "outages": [
    {
      "icon": "standard",
      "longitude": -112.121,
      "latitude": 42.439,
      "etr": "Before 04:00 AM on 03/18",
      "outCount": 1,
      "custOut": 1,
      "cause": "Investigating",
      "crewStatus": "Crews Notified",
      "reported": "01:33 AM on 03/18",
      "zip": "83234"
    },
    {
      "icon": "standard",
      "longitude": -112.02,
      "latitude": 43.425,
      "etr": "Before 04:00 AM on 03/18",
      "outCount": 1,
      "custOut": 1,
      "cause": "Investigating",
      "crewStatus": "Crews Notified",
      "reported": "01:23 AM on 03/18",
      "zip": "83404"
    },
    {
      "icon": "standard",
      "longitude": -111.941,
      "latitude": 43.455,
      "etr": "Before 04:00 AM on 03/18",
      "outCount": 2,
      "custOut": 2722,
      "cause": "Multiple outages in the area",
      "crewStatus": "Crews Arrived",
      "reported": "01:00 AM on 03/18",
      "zip": "83406, 83404, 83401, 83236"
    },
    {
      "icon": "standard",
      "longitude": -111.942,
      "latitude": 43.527,
      "etr": "Before 04:00 AM on 03/18",
      "outCount": 1,
      "custOut": 1,
      "cause": "Investigating",
      "crewStatus": "Crews Arrived",
      "reported": "01:23 AM on 03/18",
      "zip": "83401"
    },
    {
      "icon": "standard",
      "longitude": -111.684,
      "latitude": 43.616,
      "etr": "Before 06:00 AM on 03/18",
      "outCount": 1,
      "custOut": 150,
      "cause": "Investigating",
      "crewStatus": "Crews Notified",
      "reported": "03:04 AM on 03/18",
      "zip": "83443, 83442"
    }
  ],
  "zips": [
    {
      "zipCode": "83234",
      "outCountPlan": 0,
      "outCountUnplan": 1,
      "custOutPlan": 0,
      "custOutUnplan": 1
    },
    {
      "zipCode": "83236",
      "outCountPlan": 1,
      "outCountUnplan": 0,
      "custOutPlan": 69,
      "custOutUnplan": 0
    },
    {
      "zipCode": "83401",
      "outCountPlan": 1,
      "outCountUnplan": 2,
      "custOutPlan": 1,
      "custOutUnplan": 36
    },
    {
      "zipCode": "83404",
      "outCountPlan": 0,
      "outCountUnplan": 2,
      "custOutPlan": 0,
      "custOutUnplan": 64
    },
    {
      "zipCode": "83406",
      "outCountPlan": 1,
      "outCountUnplan": 1,
      "custOutPlan": 1119,
      "custOutUnplan": 1435
    },
    {
      "zipCode": "83442",
      "outCountPlan": 0,
      "outCountUnplan": 1,
      "custOutPlan": 0,
      "custOutUnplan": 4
    },
    {
      "zipCode": "83443",
      "outCountPlan": 0,
      "outCountUnplan": 1,
      "custOutPlan": 0,
      "custOutUnplan": 146
    }
  ],
  "counties": [
    {
      "countyName": "Bannock",
      "outCountPlan": 0,
      "outCountUnplan": 1,
      "custOutPlan": 0,
      "custOutUnplan": 1
    },
    {
      "countyName": "Bingham",
      "outCountPlan": 1,
      "outCountUnplan": 0,
      "custOutPlan": 18,
      "custOutUnplan": 0
    },
    {
      "countyName": "Bonneville",
      "outCountPlan": 1,
      "outCountUnplan": 4,
      "custOutPlan": 1171,
      "custOutUnplan": 1581
    },
    {
      "countyName": "Jefferson",
      "outCountPlan": 0,
      "outCountUnplan": 1,
      "custOutPlan": 0,
      "custOutUnplan": 104
    }
  ]
}
