{
  "count": 4,
  "totalState": 36,
  "outages": [
    {
      "icon": "standard",
      "longitude": -111.904,
      "latitude": 43.643,
      "etr": "Before 01:00 PM on 05/05",
      "outCount": 2,
      "custOut": 32,
      "cause": "Investigating",
      "crewStatus": "Crews Notified",
      "reported": "10:10 AM on 05/05",
      "zip": "83442"
    },
    {
      "icon": "standard",
      "longitude": -112.155,
      "latitude": 43.743,
      "etr": "Before 01:00 PM on 05/05",
      "outCount": 1,
      "custOut": 1,
      "cause": "Investigating",
      "crewStatus": "Crews Notified",
      "reported": "10:11 AM on 05/05",
      "zip": "83444"
    },
    {
      "icon": "planned",
      "longitude": -111.787,
      "latitude": 43.847,
      "etr": "Before 01:00 PM on 05/05",
      "outCount": 1,
      "custOut": 3,
      "cause": "Planned Maintenance",
      "crewStatus": "Crews Notified",
      "reported": "10:05 AM on 05/05",
      "zip": "83440"
    }
  ],
  "zips": [
    {
      "zipCode": "83440",
      "outCountPlan": 1,
      "outCountUnplan": 0,
      "custOutPlan": 3,
      "custOutUnplan": 0
    },
    {
      "zipCode": "83442",
      "outCountPlan": 0,
      "outCountUnplan": 2,
      "custOutPlan": 0,
      "custOutUnplan": 32
    },
    {
      "zipCode": "83444",
      "outCountPlan": 0,
      "outCountUnplan": 1,
      "custOutPlan": 0,
      "custOutUnplan": 1
    }
  ],
  "counties": [
    {
      "countyName": "Jefferson",
      "outCountPlan": 0,
      "outCountUnplan": 3,
      "custOutPlan": 0,
      "custOutUnplan": 33
    },
    {
      "countyName": "Madison",
      "outCountPlan": 1,
      "outCountUnplan": 0,
      "custOutPlan": 3,
      "custOutUnplan": 0
    }
  ]
}
