{
  "count": 34,
  "totalState": 1305,
  "outages": [
    {
      "icon": "standard",
      "longitude": -113.751,
      "latitude": 37.17,
      "etr": "Before 03:00 PM on 08/22",
      "outCount": 1,
      "custOut": 1,
      "cause": "Investigating",
      "crewStatus": "Crews Notified",
      "reported": "12:30 PM on 08/22",
      "zip": "84738"
    },
    {
      "icon": "standard",
      "longitude": -109.286,
      "latitude": 37.451,
      "etr": "Assessing",
      "outCount": 1,
      "custOut": 1,
      "cause": "Investigating",
      "crewStatus": "Crews Notified",
      "reported": "08:52 AM on 08/22",
      "zip": "84511"
    },
    {
      "icon": "planned",
      "longitude": -113.122,
      "latitude": 37.684,
      "etr": "Before 02:00 PM on 08/22",
      "outCount": 1,
      "custOut": 1,
      "cause": "Planned Maintenance",
      "crewStatus": "Crews Arrived",
      "reported": "12:28 PM on 08/22",
      "zip": "84721"
    },
    {
      "icon": "planned",
      "longitude": -109.455,
      "latitude": 38.505,
      "etr": "Before 02:30 PM on 08/22",
      "outCount": 1,
      "custOut": 8,
      "cause": "Planned Maintenance",
      "crewStatus": "Crews Arrived",
      "reported": "09:48 AM on 08/22",
      "zip": "84532"
    },
    {
      "icon": "standard",
      "longitude": -109.368,
      "latitude": 38.67,
      "etr": "Assessing",
      "outCount": 1,
      "custOut": 1,
      "cause": "Investigating",
      "crewStatus": "Crews Notified",
      "reported": "07:24 AM on 08/22",
      "zip": "84532"
    },
    {
      "icon": "standard",
      "longitude": -109.723,
      "latitude": 38.972,
      "etr": "Assessing",
      "outCount": 1,
      "custOut": 1,
      "cause": "Investigating",
      "crewStatus": "Crews Notified",
      "reported": "09:38 AM on 08/22",
      "zip": "84540"
    },
    {
      "icon": "standard",
      "longitude": -111.154,
      "latitude": 39.095,
      "etr": "Before 05:30 PM on 08/22",
      "outCount": 1,
      "custOut": 1,
      "cause": "Investigating",
      "crewStatus": "Crews Notified",
      "reported": "09:07 AM on 08/22",
      "zip": "84523"
    },
    {
      "icon": "planned",
      "longitude": -113.046,
      "latitude": 39.186,
      "etr": "Before 02:30 PM on 08/22",
      "outCount": 1,
      "custOut": 5,
      "cause": "Planned Maintenance",
      "crewStatus": "Crews Arrived",
      "reported": "07:04 AM on 08/22",
      "zip": "84728"
    },
    {
      "icon": "standard",
      "longitude": -112.009,
      "latitude": 40.309,
      "etr": "Before 01:30 PM on 08/22",
      "outCount": 1,
      "custOut": 1,
      "cause": "Investigating",
      "crewStatus": "Crews Notified",
      "reported": "10:42 AM on 08/22",
      "zip": "84005"
    },
    {
      "icon": "planned",
      "longitude": -109.488,
      "latitude": 40.405,
      "etr": "Before 02:00 PM on 08/22",
      "outCount": 2,
      "custOut": 6,
      "cause": "Planned Maintenance",
      "crewStatus": "Crews Arrived",
      "reported": "12:05 PM on 08/22",
      "zip": "84078"
    },
    {
      "icon": "planned",
      "longitude": -111.859,
      "latitude": 40.448,
      "etr": "Before 02:30 PM on 08/22",
      "outCount": 1,
      "custOut": 12,
      "cause": "Planned Maintenance",
      "crewStatus": "Crews Arrived",
      "reported": "08:25 AM on 08/22",
      "zip": "84043"
    },
    {
      "icon": "standard",
      "longitude": -111.974,
      "latitude": 40.498,
      "etr": "Before 04:00 PM on 08/22",
      "outCount": 1,
      "custOut": 1,
      "cause": "Investigating",
      "crewStatus": "Crews Notified",
      "reported": "12:45 PM on 08/22",
      "zip": "84065"
    },
    {
      "icon": "standard",
      "longitude": -112.279,
      "latitude": 40.553,
      "etr": "Before 02:00 PM on 08/22",
      "outCount": 1,
      "custOut": 1,
      "cause": "Investigating",
      "crewStatus": "Crews Arrived",
      "reported": "07:55 AM on 08/22",
      "zip": "84074"
    },
    {
      "icon": "standard",
      "longitude": -111.843,
      "latitude": 40.615,
      "etr": "Before 03:30 PM on 08/22",
      "outCount": 1,
      "custOut": 1,
      "cause": "Investigating",
      "crewStatus": "Crews Notified",
      "reported": "12:17 PM on 08/22",
      "zip": "84093"
    },
    {
      "icon": "standard",
      "longitude": -111.823,
      "latitude": 40.615,
      "etr": "Before 03:00 PM on 08/22",
      "outCount": 1,
      "custOut": 1,
      "cause": "Investigating",
      "crewStatus": "Crews Arrived",
      "reported": "11:41 AM on 08/22",
      "zip": "84121"
    },
    {
      "icon": "standard",
      "longitude": -112.299,
      "latitude": 40.625,
      "etr": "Before 06:00 PM on 08/22",
      "outCount": 1,
      "custOut": 1,
      "cause": "Investigating",
      "crewStatus": "Crews Notified",
      "reported": "11:44 AM on 08/22",
      "zip": "84074"
    },
    {
      "icon": "standard",
      "longitude": -111.824,
      "latitude": 40.658,
      "etr": "Before 03:30 PM on 08/22",
      "outCount": 2,
      "custOut": 2,
      "cause": "Investigating",
      "crewStatus": "Crews Notified",
      "reported": "12:16 PM on 08/22",
      "zip": "84117"
    },
    {
      "icon": "standard",
      "longitude": -111.881,
      "latitude": 40.672,
      "etr": "Before 03:30 PM on 08/22",
      "outCount": 1,
      "custOut": 4,
      "cause": "Investigating",
      "crewStatus": "Crews Arrived",
      "reported": "11:26 AM on 08/22",
      "zip": "84107"
    },
    {
      "icon": "planned",
      "longitude": -111.824,
      "latitude": 40.673,
      "etr": "Before 03:00 PM on 08/22",
      "outCount": 1,
      "custOut": 4,
      "cause": "Planned Maintenance",
      "crewStatus": "Crews Arrived",
      "reported": "09:05 AM on 08/22",
      "zip": "84124"
    },
    {
      "icon": "standard",
      "longitude": -112.262,
      "latitude": 40.683,
      "etr": "Before 05:00 PM on 08/22",
      "outCount": 1,
      "custOut": 1,
      "cause": "Investigating",
      "crewStatus": "Crews Notified",
      "reported": "10:59 AM on 08/22",
      "zip": "84074"
    },
    {
      "icon": "standard",
      "longitude": -111.824,
      "latitude": 40.687,
      "etr": "Before 04:00 PM on 08/22",
      "outCount": 1,
      "custOut": 1,
      "cause": "Investigating",
      "crewStatus": "Crews Notified",
      "reported": "12:35 PM on 08/22",
      "zip": "84124"
    },
    {
      "icon": "standard",
      "longitude": -111.901,
      "latitude": 40.716,
      "etr": "Before 02:30 PM on 08/22",
      "outCount": 1,
      "custOut": 1,
      "cause": "Investigating",
      "crewStatus": "Crews Arrived",
      "reported": "11:16 AM on 08/22",
      "zip": "84115"
    },
    {
      "icon": "standard",
      "longitude": -111.863,
      "latitude": 40.716,
      "etr": "Before 03:30 PM on 08/22",
      "outCount": 1,
      "custOut": 1,
      "cause": "Investigating",
      "crewStatus": "Crews Notified",
      "reported": "12:23 PM on 08/22",
      "zip": "84106"
    },
    {
      "icon": "standard",
      "longitude": -111.501,
      "latitude": 40.733,
      "etr": "Before 05:30 PM on 08/22",
      "outCount": 1,
      "custOut": 1123,
      "cause": "Investigating",
      "crewStatus": "Crews Notified",
      "reported": "12:32 PM on 08/22",
      "zip": "84098, 84017"
    },
    {
      "icon": "standard",
      "longitude": -111.882,
      "latitude": 40.745,
      "etr": "Before 03:00 PM on 08/22",
      "outCount": 1,
      "custOut": 1,
      "cause": "Investigating",
      "crewStatus": "Crews Notified",
      "reported": "11:51 AM on 08/22",
      "zip": "84115"
    },
    {
      "icon": "planned",
      "longitude": -111.864,
      "latitude": 40.774,
      "etr": "Before 03:00 PM on 08/22",
      "outCount": 1,
      "custOut": 22,
      "cause": "Planned Maintenance",
      "crewStatus": "Crews Arrived",
      "reported": "10:12 AM on 08/22",
      "zip": "84102"
    },
    {
      "icon": "standard",
      "longitude": -111.921,
      "latitude": 40.788,
      "etr": "Before 04:00 PM on 08/22",
      "outCount": 1,
      "custOut": 1,
      "cause": "Investigating",
      "crewStatus": "Crews Notified",
      "reported": "12:39 PM on 08/22",
      "zip": "84116"
    },
    {
      "icon": "standard",
      "longitude": -111.965,
      "latitude": 41.208,
      "etr": "Before 02:00 PM on 08/22",
      "outCount": 1,
      "custOut": 1,
      "cause": "Emergency Repair",
      "crewStatus": "Crews Arrived",
      "reported": "12:39 PM on 08/22",
      "zip": "84401"
    },
    {
      "icon": "standard",
      "longitude": -112.005,
      "latitude": 41.28,
      "etr": "Before 02:30 PM on 08/22",
      "outCount": 1,
      "custOut": 1,
      "cause": "Investigating",
      "crewStatus": "Crews Arrived",
      "reported": "11:18 AM on 08/22",
      "zip": "84404"
    },
    {
      "icon": "planned",
      "longitude": -111.832,
      "latitude": 41.31,
      "etr": "Before 02:30 PM on 08/22",
      "outCount": 1,
      "custOut": 81,
      "cause": "Planned Maintenance",
      "crewStatus": "Crews Arrived",
      "reported": "09:30 AM on 08/22",
      "zip": "84310"
    },
    {
      "icon": "planned",
      "longitude": -112.086,
      "latitude": 41.569,
      "etr": "Before 01:30 PM on 08/22",
      "outCount": 1,
      "custOut": 17,
      "cause": "Planned Maintenance",
      "crewStatus": "Crews Arrived",
      "reported": "10:02 AM on 08/22",
      "zip": "84302"
    },
    {
      "icon": "standard",
      "longitude": -111.837,
      "latitude": 41.658,
      "etr": "Before 04:00 PM on 08/22",
      "outCount": 1,
      "custOut": 1,
      "cause": "Emergency Repair",
      "crewStatus": "Crews Arrived",
      "reported": "12:41 PM on 08/22",
      "zip": "84321"
    }
  ],
  "zips": [
    {
      "zipCode": "84005",
      "outCountPlan": 0,
      "outCountUnplan": 1,
      "custOutPlan": 0,
      "custOutUnplan": 1
    },
    {
      "zipCode": "84017",
      "outCountPlan": 0,
      "outCountUnplan": 1,
      "custOutPlan": 0,
      "custOutUnplan": 546
    },
    {
      "zipCode": "84043",
      "outCountPlan": 1,
      "outCountUnplan": 0,
      "custOutPlan": 12,
      "custOutUnplan": 0
    },
    {
      "zipCode": "84065",
      "outCountPlan": 0,
      "outCountUnplan": 1,
      "custOutPlan": 0,
      "custOutUnplan": 1
    },
    {
      "zipCode": "84074",
      "outCountPlan": 0,
      "outCountUnplan": 3,
      "custOutPlan": 0,
      "custOutUnplan": 3
    },
    {
      "zipCode": "84078",
      "outCountPlan": 2,
      "outCountUnplan": 0,
      "custOutPlan": 6,
      "custOutUnplan": 0
    },
    {
      "zipCode": "84093",
      "outCountPlan": 0,
      "outCountUnplan": 1,
      "custOutPlan": 0,
      "custOutUnplan": 1
    },
    {
      "zipCode": "84098",
      "outCountPlan": 0,
      "outCountUnplan": 1,
      "custOutPlan": 0,
      "custOutUnplan": 577
    },
    {
      "zipCode": "84102",
      "outCountPlan": 1,
      "outCountUnplan": 0,
      "custOutPlan": 22,
      "custOutUnplan": 0
    },
    {
      "zipCode": "84106",
      "outCountPlan": 0,
      "outCountUnplan": 1,
      "custOutPlan": 0,
      "custOutUnplan": 1
    },
    {
      "zipCode": "84107",
      "outCountPlan": 0,
      "outCountUnplan": 1,
      "custOutPlan": 0,
      "custOutUnplan": 4
    },
    {
      "zipCode": "84115",
      "outCountPlan": 0,
      "outCountUnplan": 2,
      "custOutPlan": 0,
      "custOutUnplan": 2
    },
    {
      "zipCode": "84116",
      "outCountPlan": 0,
      "outCountUnplan": 1,
      "custOutPlan": 0,
      "custOutUnplan": 1
    },
    {
      "zipCode": "84117",
      "outCountPlan": 0,
      "outCountUnplan": 2,
      "custOutPlan": 0,
      "custOutUnplan": 2
    },
    {
      "zipCode": "84121",
      "outCountPlan": 0,
      "outCountUnplan": 1,
      "custOutPlan": 0,
      "custOutUnplan": 1
    },
    {
      "zipCode": "84124",
      "outCountPlan": 1,
      "outCountUnplan": 1,
      "custOutPlan": 4,
      "custOutUnplan": 1
    },
    {
      "zipCode": "84302",
      "outCountPlan": 1,
      "outCountUnplan": 0,
      "custOutPlan": 17,
      "custOutUnplan": 0
    },
    {
      "zipCode": "84310",
      "outCountPlan": 1,
      "outCountUnplan": 0,
      "custOutPlan": 81,
      "custOutUnplan": 0
    },
    {
      "zipCode": "84321",
      "outCountPlan": 0,
      "outCountUnplan": 1,
      "custOutPlan": 0,
      "custOutUnplan": 1
    },
    {
      "zipCode": "84401",
      "outCountPlan": 0,
      "outCountUnplan": 1,
      "custOutPlan": 0,
      "custOutUnplan": 1
    },
    {
      "zipCode": "84404",
      "outCountPlan": 0,
      "outCountUnplan": 1,
      "custOutPlan": 0,
      "custOutUnplan": 1
    },
    {
      "zipCode": "84511",
      "outCountPlan": 0,
      "outCountUnplan": 1,
      "custOutPlan": 0,
      "custOutUnplan": 1
    },
    {
      "zipCode": "84523",
      "outCountPlan": 0,
      "outCountUnplan": 1,
      "custOutPlan": 0,
      "custOutUnplan": 1
    },
    {
      "zipCode": "84532",
      "outCountPlan": 1,
      "outCountUnplan": 1,
      "custOutPlan": 8,
      "custOutUnplan": 1
    },
    {
      "zipCode": "84540",
      "outCountPlan": 0,
      "outCountUnplan": 1,
      "custOutPlan": 0,
      "custOutUnplan": 1
    },
    {
      "zipCode": "84721",
      "outCountPlan": 1,
      "outCountUnplan": 0,
      "custOutPlan": 1,
      "custOutUnplan": 0
    },
    {
      "zipCode": "84728",
      "outCountPlan": 1,
      "outCountUnplan": 0,
      "custOutPlan": 5,
      "custOutUnplan": 0
    },
    {
      "zipCode": "84738",
      "outCountPlan": 0,
      "outCountUnplan": 1,
      "custOutPlan": 0,
      "custOutUnplan": 1
    }
  ],
  "counties": [
    {
      "countyName": "Box Elder",
      "outCountPlan": 1,
      "outCountUnplan": 0,
      "custOutPlan": 17,
      "custOutUnplan": 0
    },
    {
      "countyName": "Cache",
      "outCountPlan": 0,
      "outCountUnplan": 1,
      "custOutPlan": 0,
      "custOutUnplan": 1
    },
    {
      "countyName": "Emery",
      "outCountPlan": 0,
      "outCountUnplan": 1,
      "custOutPlan": 0,
      "custOutUnplan": 1
    },
    {
      "countyName": "Grand",
      "outCountPlan": 0,
      "outCountUnplan": 2,
      "custOutPlan": 0,
      "custOutUnplan": 2
    },
    {
      "countyName": "Iron",
      "outCountPlan": 1,
      "outCountUnplan": 0,
      "custOutPlan": 1,
      "custOutUnplan": 0
    },
    {
      "countyName": "Millard",
      "outCountPlan": 1,
      "outCountUnplan": 0,
      "custOutPlan": 5,
      "custOutUnplan": 0
    },
    {
      "countyName": "Morgan",
      "outCountPlan": 0,
      "outCountUnplan": 1,
      "custOutPlan": 0,
      "custOutUnplan": 11
    },
    {
      "countyName": "Salt Lake",
      "outCountPlan": 2,
      "outCountUnplan": 11,
      "custOutPlan": 26,
      "custOutUnplan": 14
    },
    {
      "countyName": "San Juan",
      "outCountPlan": 1,
      "outCountUnplan": 1,
      "custOutPlan": 8,
      "custOutUnplan": 1
    },
    {
      "countyName": "Summit",
      "outCountPlan": 0,
      "outCountUnplan": 1,
      "custOutPlan": 0,
      "custOutUnplan": 1112
    },
    {
      "countyName": "Tooele",
      "outCountPlan": 0,
      "outCountUnplan": 3,
      "custOutPlan": 0,
      "custOutUnplan": 3
    },
    {
      "countyName": "Uintah",
      "outCountPlan": 2,
      "outCountUnplan": 0,
      "custOutPlan": 6,
      "custOutUnplan": 0
    },
    {
      "countyName": "Utah",
      "outCountPlan": 1,
      "outCountUnplan": 1,
      "custOutPlan": 12,
      "custOutUnplan": 1
    },
    {
      "countyName": "Washington",
      "outCountPlan": 0,
      "outCountUnplan": 1,
      "custOutPlan": 0,
      "custOutUnplan": 1
    },
    {
      "countyName": "Weber",
      "outCountPlan": 1,
      "outCountUnplan": 2,
      "custOutPlan": 81,
      "custOutUnplan": 2
    }
  ]
}
