{
  "count": 3,
  "totalState": 3,
  "outages": [
    {
      "icon": "standard",
      "longitude": -111.783,
      "latitude": 40.368,
      "etr": "Before 08:00 AM on 07/07",
      "outCount": 1,
      "custOut": 1,
      "cause": "Investigating",
      "crewStatus": "Crews Notified",
      "reported": "05:25 AM on 07/07",
      "zip": "84003"
    },
    {
      "icon": "standard",
      "longitude": -111.946,
      "latitude": 41.194,
      "etr": "Before 08:00 AM on 07/07",
      "outCount": 1,
      "custOut": 1,
      "cause": "Investigating",
      "crewStatus": "Crews Notified",
      "reported": "04:49 AM on 07/07",
      "zip": "84403"
    },
    {
      "icon": "standard",
      "longitude": -111.946,
      "latitude": 41.208,
      "etr": "Before 07:00 AM on 07/07",
      "outCount": 1,
      "custOut": 1,
      "cause": "Investigating",
      "crewStatus": "Crews Notified",
      "reported": "03:46 AM on 07/07",
      "zip": "84403"
    }
  ],
  "zips": [
    {
      "zipCode": "84003",
      "outCountPlan": 0,
      "outCountUnplan": 1,
      "custOutPlan": 0,
      "custOutUnplan": 1
    },
    {
      "zipCode": "84403",
      "outCountPlan": 0,
      "outCountUnplan": 2,
      "custOutPlan": 0,
      "custOutUnplan": 2
    }
  ],
  "counties": [
    {
      "countyName": "Utah",
      "outCountPlan": 0,
      "outCountUnplan": 1,
      "custOutPlan": 0,
      "custOutUnplan": 1
    },
    {
      "countyName": "Weber",
      "outCountPlan": 0,
      "outCountUnplan": 2,
      "custOutPlan": 0,
      "custOutUnplan": 2
    }
  ]
}
